imexam/__init__.py
imexam/_astropy_init.py
imexam/connect.py
imexam/ds9_viewer.py
imexam/ginga_viewer.py
imexam/imexam_defpars.py
imexam/imexamine.py
imexam/imexamxpa.cpython-37m-darwin.so
imexam/math_helper.py
imexam/util.py
imexam/xpa_wrap.py
imexam-0.9.1.dist-info/METADATA
imexam-0.9.1.dist-info/WHEEL
imexam-0.9.1.dist-info/top_level.txt
imexam-0.9.1.dist-info/RECORD
